pyntegrate/__init__.py
pyntegrate/__version__.py
pyntegrate/arctan.cpython-310-x86_64-linux-gnu.so
pyntegrate/pyarctan.py
pyntegrate-1.3.6.data/scripts/pyarctan.py
pyntegrate-1.3.6.dist-info/LICENSE
pyntegrate-1.3.6.dist-info/METADATA
pyntegrate-1.3.6.dist-info/WHEEL
pyntegrate-1.3.6.dist-info/top_level.txt
pyntegrate-1.3.6.dist-info/RECORD
