Metadata-Version: 2.1
Name: pyntegrate
Version: 1.3.6
Summary: Pyntegrate is an example of various sorting algorithms and other functions using C Extensions.
Home-page: https://github.com/rtsfred3/pyntegrate
Author: Ryan Fredrickson
Author-email: rtsfred3@gmail.com
License: UNKNOWN
Download-URL: https://pypi.org/project/pyntegrate/
Project-URL: Bug Tracker, https://github.com/rtsfred3/pyntegrate/issues
Project-URL: Source Code, https://github.com/rtsfred3/pyntegrate
Keywords: pyntegrate Python C CPython
Platform: UNKNOWN
Classifier: Programming Language :: Python :: 3
Classifier: Programming Language :: Python :: Implementation :: CPython
Classifier: Programming Language :: C
Classifier: License :: OSI Approved :: Apache Software License
Classifier: Operating System :: OS Independent
Requires-Python: >=3.7
